streamlithelpers/__init__.py
streamlithelpers/streamlit_helpers.py
streamlithelpers-0.4.2.dist-info/LICENSE.txt
streamlithelpers-0.4.2.dist-info/METADATA
streamlithelpers-0.4.2.dist-info/WHEEL
streamlithelpers-0.4.2.dist-info/top_level.txt
streamlithelpers-0.4.2.dist-info/RECORD
