Metadata-Version: 2.1
Name: streamlithelpers
Version: 0.4.2
Summary: Simple utilities to help streamlit app development
Home-page: https://github.com/andehr/streamlit-helpers
Download-URL: https://github.com/andehr/streamlit-helpers/archive/refs/tags/v0.2.1.tar.gz
Author: Andrew Robertson
Author-email: 
License: MIT
Keywords: streamlit,utility
Classifier: Development Status :: 4 - Beta
Classifier: Intended Audience :: Developers
Classifier: License :: OSI Approved :: MIT License
Classifier: Programming Language :: Python :: 3.10
License-File: LICENSE.txt
Requires-Dist: pandas
Requires-Dist: streamlit
Requires-Dist: streamlit-extras
Requires-Dist: streamlit-ace
